raspberrypi/__init__.py
raspberrypi/main.py
raspberrypi/util.py
raspberrypi-0.1.9.dist-info/LICENSE
raspberrypi-0.1.9.dist-info/METADATA
raspberrypi-0.1.9.dist-info/WHEEL
raspberrypi-0.1.9.dist-info/entry_points.txt
raspberrypi-0.1.9.dist-info/top_level.txt
raspberrypi-0.1.9.dist-info/RECORD
