Metadata-Version: 2.1
Name: raspberrypi
Version: 0.1.9
Summary: A Raspberry Pi Toolkit.
Home-page: https://leesoar.com
Author: leesoar
Author-email: secure@tom.com
License: MIT
Keywords: raspberrypi,raspberry
Platform: UNKNOWN
Classifier: License :: OSI Approved :: MIT License
Classifier: Programming Language :: Python :: 3.5
Classifier: Programming Language :: Python :: 3.6
Classifier: Programming Language :: Python :: 3.7
Classifier: Programming Language :: Python :: Implementation :: CPython
Classifier: Programming Language :: Python :: Implementation :: PyPy
Requires-Python: >=3.3.0
